Metadata-Version: 1.0
Name: bl-title-amaz
Version: 0.0.2
Summary: bl-title-amaz
Home-page: UNKNOWN
Author: UNKNOWN
Author-email: lion@bluehack.net
License: UNKNOWN
Keywords: BlueLens,bl-product-amaz
Platform: UNKNOWN
